{
  "conceptrecid": "8052838",
  "metadata": {
    "access_right": "open",
    "creators": [
      {
        "affiliation": "Center for Astrophysics | Harvard & Smithsonian",
        "name": "Williams, Peter K. G.",
        "orcid": "0000-0003-3734-3587"
      },
      {
        "affiliation": "Institut de Planétologie et d’Astrophysique de Grenoble",
        "name": "Clavel, Maïca",
        "orcid": "0000-0003-0724-2742"
      },
      {
        "affiliation": "Dartmouth College",
        "name": "Newton, Elisabeth R.",
        "orcid": "0000-0003-4150-841X"
      },
      {
        "name": "Ryzhkov, Denis"
      }
    ],
    "description": "pwkit is a collection of astronomical utilities created by Peter Williams. Learn more at <a href=\"https://pwkit.readthedocs.io/\">the pwkit website</a>.",
    "keywords": [
      "Astronomy",
      "Python",
      "Visualization"
    ],
    "language": "eng",
    "license": "MIT",
    "publication_date": "2023-06-18",
    "title": "pwkit 1.2.0",
    "upload_type": "software",
    "version": "1.2.0"
  },
  "conceptdoi": "10.5281/zenodo.8052838",
  "record_id": "8052937",
  "doi": "10.5281/zenodo.8052937",
  "bucket_link": "https://zenodo.org/api/files/355c89ba-b49c-4ead-a3bb-2f3055c53d01"
}
